{
  "theme": {
    "id": "kosakata",
    "name": "Kosa Kata",
    "tagline": "Vocabulary — the lever that pays off across every paper"
  },
  "topics": {
    "kosa-kata": {
      "id": "kosa-kata",
      "title": "Kosa Kata Tematik",
      "themes": ["kosakata"],
      "levels": ["P5", "P6"],
      "blurb": "Bank perbendaharaan kata mengikut tema: emosi, pergerakan, sifat, latar, komuniti, sekolah, kesihatan.",
      "keyQuestions": [
        "Mengapakah pelajar PSLE perlu mempelbagaikan kosa kata dalam karangan?",
        "Apakah perbezaan antara 'gembira', 'sukacita', dan 'teruja'?",
        "Bagaimanakah kosa kata yang luas membantu kefahaman dalam Kertas 2B?"
      ],
      "glossary": [
        { "term": "gembira", "definition": "Happy; perasaan yang menyenangkan.", "template": "Hatinya berasa gembira menerima hadiah itu." },
        { "term": "sukacita", "definition": "Joyful, delighted; lebih formal daripada gembira.", "template": "Dengan penuh sukacita, dia berlari ke pelukan ibunya." },
        { "term": "teruja", "definition": "Excited; bersemangat tinggi.", "template": "Dia berasa teruja menanti percutian sekolah." },
        { "term": "girang", "definition": "Cheerful, elated.", "template": "Wajahnya kelihatan girang setelah lulus peperiksaan." },
        { "term": "riang", "definition": "Lighthearted, merry.", "template": "Suasana di taman menjadi riang." },
        { "term": "bangga", "definition": "Proud.", "template": "Ibunya berasa bangga dengan pencapaiannya." },
        { "term": "lega", "definition": "Relieved.", "template": "Dia menghela nafas lega setelah selamat tiba." },
        { "term": "terharu", "definition": "Moved, touched emotionally.", "template": "Air matanya bergenang terharu mendengar berita itu." },
        { "term": "bersyukur", "definition": "Grateful.", "template": "Kami bersyukur atas pertolongan jiran." },
        { "term": "tenang", "definition": "Calm, peaceful.", "template": "Hatinya terasa tenang di tepi pantai." },

        { "term": "sedih", "definition": "Sad.", "template": "Wajahnya kelihatan sedih kerana kehilangan haiwan peliharaan." },
        { "term": "pilu", "definition": "Sorrowful, heartbroken.", "template": "Hatinya terasa pilu mendengar pesanan itu." },
        { "term": "dukacita", "definition": "Grief, sorrow; lebih kuat daripada sedih.", "template": "Berita itu memenuhi hatinya dengan dukacita." },
        { "term": "murung", "definition": "Gloomy, dejected.", "template": "Dia kelihatan murung sepanjang hari." },
        { "term": "bimbang", "definition": "Worried.", "template": "Ibu bimbang akan keselamatan anaknya." },
        { "term": "risau", "definition": "Concerned.", "template": "Dia risau akan keputusan peperiksaan." },
        { "term": "cemas", "definition": "Anxious, apprehensive.", "template": "Jantungnya berdegup cemas." },
        { "term": "takut", "definition": "Afraid.", "template": "Adik takut kepada anjing besar itu." },
        { "term": "gentar", "definition": "Trembling with fear; lebih sastera daripada takut.", "template": "Kakinya terasa gentar." },
        { "term": "ngeri", "definition": "Horrified, terrified.", "template": "Dia berasa ngeri melihat kemalangan itu." },
        { "term": "marah", "definition": "Angry.", "template": "Ayah marah kerana saya lewat pulang." },
        { "term": "geram", "definition": "Frustrated, annoyed.", "template": "Hatinya geram dengan kelakuan adik." },
        { "term": "kecewa", "definition": "Disappointed.", "template": "Dia kecewa kerana tidak berjaya." },
        { "term": "malu", "definition": "Embarrassed, ashamed.", "template": "Wajahnya merah kerana malu." },
        { "term": "tersipu-sipu", "definition": "Bashful, blushing.", "template": "Dia tersenyum tersipu-sipu apabila dipuji." },

        { "term": "berlari", "definition": "To run.", "template": "Adik berlari mengejar bola." },
        { "term": "bergegas", "definition": "To hurry, rush.", "template": "Ibu bergegas ke kedai sebelum hujan turun." },
        { "term": "tergesa-gesa", "definition": "In a hurry; rushing.", "template": "Dia bergegas tergesa-gesa ke sekolah." },
        { "term": "melompat", "definition": "To jump.", "template": "Kanak-kanak itu melompat dengan gembira." },
        { "term": "memanjat", "definition": "To climb.", "template": "Monyet memanjat pokok kelapa." },
        { "term": "menghampiri", "definition": "To approach.", "template": "Saya menghampirinya untuk memberi salam." },
        { "term": "terjatuh", "definition": "To fall (accidentally).", "template": "Adik terjatuh di tangga." },
        { "term": "tersungkur", "definition": "To fall face-first.", "template": "Dia tersungkur kerana tersepak batu." },
        { "term": "tersandung", "definition": "To stumble.", "template": "Saya tersandung dan hampir jatuh." },
        { "term": "melangkah", "definition": "To step.", "template": "Beliau melangkah dengan yakin ke pentas." },
        { "term": "berundur", "definition": "To retreat, step back.", "template": "Penjenayah itu berundur apabila polis tiba." },
        { "term": "melarikan diri", "definition": "To flee, escape.", "template": "Tawanan itu cuba melarikan diri." },

        { "term": "mengangguk", "definition": "To nod.", "template": "Saya mengangguk tanda bersetuju." },
        { "term": "menggeleng", "definition": "To shake head.", "template": "Adik menggeleng — dia tidak mahu pergi." },
        { "term": "tersenyum", "definition": "To smile.", "template": "Cikgu tersenyum melihat kerja saya." },
        { "term": "tergelak", "definition": "To laugh out loud.", "template": "Kami tergelak mendengar lawak datuk." },
        { "term": "menangis", "definition": "To cry.", "template": "Bayi itu menangis kerana lapar." },
        { "term": "meraung", "definition": "To wail, sob loudly.", "template": "Dia meraung apabila kehilangan kucingnya." },
        { "term": "teresak-esak", "definition": "To sob uncontrollably.", "template": "Dia menangis teresak-esak di pelukan ibunya." },
        { "term": "terpinga-pinga", "definition": "Dazed, confused.", "template": "Saya terpinga-pinga melihat soalan yang sukar itu." },
        { "term": "ternganga", "definition": "Open-mouthed, shocked.", "template": "Mulutnya ternganga melihat keajaiban itu." },
        { "term": "tersentak", "definition": "Startled.", "template": "Saya tersentak dengan bunyi guruh yang kuat." },

        { "term": "rajin", "definition": "Diligent, hardworking.", "template": "Pelajar yang rajin sentiasa berjaya." },
        { "term": "tekun", "definition": "Diligent, persevering (sinonim formal).", "template": "Beliau tekun belajar selama bertahun-tahun." },
        { "term": "berani", "definition": "Brave, courageous.", "template": "Anak muda itu berani membantu orang dewasa." },
        { "term": "jujur", "definition": "Honest.", "template": "Berlaku jujur dalam setiap perbuatan." },
        { "term": "ikhlas", "definition": "Sincere.", "template": "Pertolongan diberikan dengan ikhlas." },
        { "term": "bertanggungjawab", "definition": "Responsible.", "template": "Pelajar yang bertanggungjawab menyiapkan kerja rumahnya." },
        { "term": "penyayang", "definition": "Loving, caring.", "template": "Ibu seorang yang penyayang." },
        { "term": "pemurah", "definition": "Generous.", "template": "Pak Cik Salleh pemurah dengan jirannya." },
        { "term": "sabar", "definition": "Patient.", "template": "Sabar adalah kunci ketenangan hati." },
        { "term": "baik hati", "definition": "Kind-hearted.", "template": "Wanita baik hati itu menolong saya." },
        { "term": "bijaksana", "definition": "Wise.", "template": "Datuk membuat keputusan yang bijaksana." },
        { "term": "peramah", "definition": "Friendly.", "template": "Encik Rahman peramah dengan semua jiran." },
        { "term": "amanah", "definition": "Trustworthy.", "template": "Pemimpin yang amanah dihormati ramai." },
        { "term": "adil", "definition": "Fair, just.", "template": "Cikgu adil dalam memberi markah." },

        { "term": "matahari bersinar terik", "definition": "The sun blazes hot.", "template": "Pagi itu, matahari bersinar terik membakar kulit." },
        { "term": "hujan lebat", "definition": "Heavy rain.", "template": "Hujan lebat mengguyur bumi sepanjang petang." },
        { "term": "hujan renyai-renyai", "definition": "Drizzle.", "template": "Hujan renyai-renyai tidak menghalang kami daripada keluar." },
        { "term": "angin bertiup kencang", "definition": "Strong wind blows.", "template": "Angin bertiup kencang menandakan ribut akan datang." },
        { "term": "langit mendung", "definition": "Overcast sky.", "template": "Langit mendung sejak pagi tadi." },
        { "term": "cuaca cerah", "definition": "Clear weather.", "template": "Hari ini cuaca cerah, sesuai untuk berkelah." },
        { "term": "ombak bergelora", "definition": "Crashing waves.", "template": "Ombak bergelora menjadikan pantai itu berbahaya." },
        { "term": "pemandangan yang indah", "definition": "Beautiful scenery.", "template": "Pemandangan yang indah memukau di Pulau Tioman." },
        { "term": "suasana meriah", "definition": "Lively atmosphere.", "template": "Suasana di majlis perkahwinan itu sangat meriah." },
        { "term": "suasana mencengkam", "definition": "Tense atmosphere.", "template": "Suasana menjadi mencengkam apabila berita itu sampai." },
        { "term": "penuh sesak", "definition": "Crowded.", "template": "Stesen MRT penuh sesak pada waktu puncak." },
        { "term": "sunyi sepi", "definition": "Quiet, deserted.", "template": "Pada lewat malam, jalan itu sunyi sepi." },

        { "term": "gotong-royong", "definition": "Communal cooperation.", "template": "Penduduk kampung mengadakan gotong-royong setiap bulan." },
        { "term": "perpaduan", "definition": "Unity.", "template": "Perpaduan masyarakat menjadi kunci keamanan negara." },
        { "term": "keharmonian", "definition": "Harmony.", "template": "Keharmonian keluarga sangat penting." },
        { "term": "saling menghormati", "definition": "Mutual respect.", "template": "Kita perlu saling menghormati antara satu sama lain." },
        { "term": "bertimbang rasa", "definition": "Considerate.", "template": "Anak yang bertimbang rasa membantu ibu bapanya." },
        { "term": "sukarela", "definition": "Voluntary.", "template": "Kami menyertai aktiviti sukarela di rumah anak yatim." },
        { "term": "pengorbanan", "definition": "Sacrifice.", "template": "Pengorbanan ibu bapa tidak terbalas." }
      ],
      "learnHTML": "<p>Kosa kata adalah <strong>tuas terkuat</strong> untuk meningkatkan markah PSLE Bahasa Melayu. Bank ini menyusun ~150 perkataan asas mengikut tema. Strategi pembelajaran terbaik:</p><ol style='margin-left:1.2rem;line-height:1.7'><li>Pilih satu tema setiap hari.</li><li>Cover-and-recall: tutup makna Bahasa Inggeris, sebut Bahasa Melayu, ingat semula.</li><li>Tulis 5 ayat karangan menggunakan perkataan baharu hari itu.</li><li>Tinjau semula pada hari ketujuh.</li></ol><p>Lihat <code>KosaKata_KB.md</code> dalam knowledge-base untuk senarai penuh dan ayat contoh.</p><p><strong>Petua paling penting:</strong> jangan ulang perkataan biasa seperti <em>gembira</em>, <em>sedih</em>, <em>bagus</em>, atau <em>cantik</em> dalam karangan yang sama. Setiap pengulangan = peluang untuk menonjolkan kawalan kosa kata.</p>",
      "summaryHTML": "<ul><li>Tema utama: Emosi, Pergerakan, Sifat, Latar, Komuniti, Sekolah, Keluarga, Kesihatan.</li><li>Pelbagaikan dalam karangan: <em>gembira</em> → <em>riang</em>, <em>sukacita</em>, <em>teruja</em>.</li><li>Kosa kata yang luas membuka kunci kefahaman Kertas 2B.</li><li>Latih satu tema sehari; ulang kaji mingguan.</li></ul>",
      "pslePrompts": [
        "Pada perenggan pertama karangan, tetapkan latar dengan SATU ayat suasana yang spesifik.",
        "Untuk karangan naratif klimaks, gabungkan emosi positif (terharu, lega, bangga) dengan kata kerja yang vivid.",
        "Setiap kali anda menulis 'gembira' atau 'sedih', tanya: adakah ada perkataan yang lebih tepat dari bank tematik?"
      ],
      "questions": [
        { "id": "kosa-1", "tier": "asas", "question": "Sinonim untuk 'gembira' yang lebih formal:", "options": ["happy", "sukacita", "ok", "marah"], "correct": 1, "explanation": "Sukacita = joyful, delighted (lebih formal daripada 'gembira'). Sesuai untuk karangan PSLE." },
        { "id": "kosa-2", "tier": "asas", "question": "Pilih perkataan untuk emosi negatif intensif:", "options": ["tenang", "riang", "dukacita", "lega"], "correct": 2, "explanation": "Dukacita = grief, sorrow (lebih kuat daripada 'sedih')." },
        { "id": "kosa-3", "tier": "asas", "question": "'Terharu' bermaksud:", "options": ["sangat marah", "tersentuh emosi (touched/moved)", "sangat penat", "tidak peduli"], "correct": 1, "explanation": "Terharu = secara emosi tersentuh, biasanya kerana kebaikan atau peristiwa yang menyentuh hati." },
        { "id": "kosa-4", "tier": "asas", "question": "Cuaca pagi ini sangat panas. Mana ayat yang PALING vivid?", "options": ["Cuaca panas.", "Cuaca panas sangat.", "Matahari bersinar terik.", "Hari ini hot."], "correct": 2, "explanation": "'Matahari bersinar terik' = imej yang konkrit dan vivid. Karangan cemerlang menggunakan imej, bukan hanya kata adjektif." },
        { "id": "kosa-5", "tier": "pertengahan", "question": "Pilih sinonim untuk 'rajin' yang sesuai dalam karangan formal:", "options": ["malas", "tekun", "marah", "cuai"], "correct": 1, "explanation": "Tekun = diligent, persevering. Sinonim formal untuk rajin." },
        { "id": "kosa-6", "tier": "pertengahan", "question": "Antonim untuk 'cerah':", "options": ["bersih", "gelap", "panas", "luas"], "correct": 1, "explanation": "Cerah ↔ gelap (terang ↔ gelap)." },
        { "id": "kosa-7", "tier": "pertengahan", "question": "Pilih perkataan untuk suasana yang menggambarkan ketegangan:", "options": ["meriah", "sunyi sepi", "suasana mencengkam", "bersih dan kemas"], "correct": 2, "explanation": "Suasana mencengkam = tegang, biasanya digunakan dalam karangan tentang kemalangan, pertandingan, atau peristiwa kritikal." },
        { "id": "kosa-8", "tier": "pertengahan", "question": "Mana yang BUKAN sinonim untuk 'pandai'?", "options": ["cerdik", "bijak", "bestari", "degil"], "correct": 3, "explanation": "Degil = stubborn (bukan pandai). Yang lain semua sinonim pandai." },
        { "id": "kosa-9", "tier": "mencabar", "question": "Pilih ayat karangan yang PALING matang:", "options": ["Saya rasa happy.", "Hati saya berasa amat gembira.", "Hati saya diliputi rasa sukacita yang luar biasa.", "I happy lah."], "correct": 2, "explanation": "Ayat ketiga: 'diliputi' (verb tepat) + 'rasa sukacita' (kata nama abstrak) + 'luar biasa' (penegas matang) = kosa kata terbaik." },
        { "id": "kosa-10", "tier": "mencabar", "question": "Pilih perkataan yang PALING tepat untuk slot ini: 'Apabila menerima berita kemenangan, beliau ____ sehingga air mata bergenang.'", "options": ["marah", "terharu", "kecewa", "geram"], "correct": 1, "explanation": "Air mata bergenang + berita baik → terharu (emosi positif yang menyentuh hati)." },
        { "id": "kosa-11", "tier": "mencabar", "question": "Pilih ayat dengan kata penghubung naratif PALING berkesan:", "options": ["Pada awalnya kami berkumpul. Kemudian, hujan tiba-tiba turun dengan lebatnya. Akhirnya, kami terpaksa pulang.", "Kami kumpul. Hujan datang. Kami pulang.", "Kami kumpul dan hujan datang dan kami pulang.", "Kumpul, hujan, pulang."], "correct": 0, "explanation": "Kata penghubung naratif (Pada awalnya, Kemudian, Akhirnya) mencipta aliran yang halus dan matang." },
        { "id": "kosa-12", "tier": "mencabar", "question": "Mana yang menggambarkan watak 'bertanggungjawab' dengan PALING vivid?", "options": ["Ali bertanggungjawab.", "Ali ialah seorang pelajar yang bertanggungjawab.", "Walaupun penat, Ali tetap menyiapkan kerja kumpulan sebelum tarikh akhir.", "Ali tu responsible."], "correct": 2, "explanation": "Tunjukkan, jangan sebut. Ayat ketiga menggambarkan tanggungjawab melalui aksi, bukan hanya label." }
      ]
    },

    "sinonim-antonim": {
      "id": "sinonim-antonim",
      "title": "Sinonim & Antonim",
      "themes": ["kosakata"],
      "levels": ["P5", "P6"],
      "blurb": "Pasangan kata seerti dan berlawanan — luaskan ekspresi karangan dan kefahaman.",
      "keyQuestions": [
        "Mengapakah sinonim penting untuk karangan PSLE?",
        "Apakah perbezaan antara antonim langsung dan antonim dengan 'tidak'?",
        "Bagaimanakah pengetahuan tentang sinonim membantu Kefahaman Kertas 2B?"
      ],
      "glossary": [
        { "term": "Sinonim", "definition": "Perkataan yang seerti atau hampir sama maksudnya.", "template": "gembira ↔ riang, sukacita, ceria" },
        { "term": "Antonim", "definition": "Perkataan yang berlawanan maksud.", "template": "tinggi ↔ rendah, kaya ↔ miskin" },

        { "term": "gembira (sinonim)", "definition": "Sinonim: riang, sukacita, ceria, girang.", "template": "Pelbagaikan dalam karangan." },
        { "term": "sedih (sinonim)", "definition": "Sinonim: pilu, dukacita, hiba, sayu.", "template": "Pilih register: 'pilu' lebih sastera daripada 'sedih'." },
        { "term": "marah (sinonim)", "definition": "Sinonim: berang, geram, murka.", "template": "Murka = formal/sastera." },
        { "term": "takut (sinonim)", "definition": "Sinonim: gentar, cuak, ngeri.", "template": "Ngeri = takut yang amat sangat." },
        { "term": "terkejut (sinonim)", "definition": "Sinonim: tersentak, tergamam, tercengang, terperanjat.", "template": "Pilih ikut konteks emosi." },
        { "term": "pandai (sinonim)", "definition": "Sinonim: cerdik, bijak, bestari, cerdas.", "template": "Bijak/bestari paling formal." },
        { "term": "rajin (sinonim)", "definition": "Sinonim: tekun, gigih, bersungguh-sungguh.", "template": "Tekun = paling formal." },
        { "term": "baik hati (sinonim)", "definition": "Sinonim: pemurah, penyayang, bertimbang rasa.", "template": "Konteks karangan: watak positif." },
        { "term": "cantik (sinonim)", "definition": "Sinonim: jelita, ayu, manis, rupawan.", "template": "Jelita = sastera; ayu = lembut." },
        { "term": "kacak (sinonim)", "definition": "Sinonim: tampan, segak.", "template": "Untuk lelaki." },
        { "term": "berlari (sinonim)", "definition": "Sinonim: bergegas, berkejar.", "template": "Bergegas = lebih cepat dan tergesa." },
        { "term": "berkata (sinonim)", "definition": "Sinonim: berucap, menyebut, melahirkan.", "template": "Pelbagaikan dalam dialog karangan." },
        { "term": "menjawab (sinonim)", "definition": "Sinonim: membalas, mengulas.", "template": "Konteks formal: membalas surat, mengulas pendapat." },
        { "term": "bertanya (sinonim)", "definition": "Sinonim: menyoal, mengemukakan soalan.", "template": "Menyoal = lebih formal." },
        { "term": "penat (sinonim)", "definition": "Sinonim: letih, lelah, lesu.", "template": "Letih paling biasa dalam karangan." },
        { "term": "sakit (sinonim)", "definition": "Sinonim: uzur, tenat.", "template": "Uzur = sakit tua; tenat = sakit teruk." },

        { "term": "baik ↔ jahat", "definition": "Antonim sifat utama.", "template": "Watak baik vs watak jahat dalam karangan." },
        { "term": "rajin ↔ malas", "definition": "Antonim sifat kerja.", "template": "Pelajar rajin vs malas." },
        { "term": "pandai ↔ bodoh", "definition": "Antonim kebijakan.", "template": "Dalam karangan, gunakan 'kurang pandai' yang lebih sopan." },
        { "term": "berani ↔ takut/pengecut", "definition": "Antonim keberanian.", "template": "Watak heroik vs pengecut." },
        { "term": "jujur ↔ bohong/tipu", "definition": "Antonim kejujuran.", "template": "Karangan nilai murni." },
        { "term": "kaya ↔ miskin", "definition": "Antonim kewangan.", "template": "Karangan tentang kemiskinan dan keprihatinan." },
        { "term": "sihat ↔ sakit", "definition": "Antonim kesihatan.", "template": "Karangan tentang kesihatan." },
        { "term": "tinggi ↔ rendah", "definition": "Antonim fizikal.", "template": "Bangunan tinggi vs pondok rendah." },
        { "term": "panjang ↔ pendek", "definition": "Antonim ukuran.", "template": "Jalan panjang, perjalanan pendek." },
        { "term": "besar ↔ kecil", "definition": "Antonim saiz.", "template": "Rumah besar, bilik kecil." },
        { "term": "luas ↔ sempit", "definition": "Antonim ruang.", "template": "Padang luas vs jalan sempit." },
        { "term": "tebal ↔ nipis", "definition": "Antonim ketebalan.", "template": "Buku tebal, kertas nipis." },
        { "term": "cerah ↔ gelap", "definition": "Antonim cahaya.", "template": "Pagi cerah, malam gelap." },
        { "term": "bersih ↔ kotor", "definition": "Antonim kebersihan.", "template": "Bilik bersih vs tempat kotor." },
        { "term": "muda ↔ tua", "definition": "Antonim umur.", "template": "Pemuda vs orang tua." },
        { "term": "naik ↔ turun", "definition": "Antonim arah.", "template": "Naik bukit, turun lembah." },
        { "term": "menang ↔ kalah", "definition": "Antonim pertandingan.", "template": "Pasukan menang, lawan kalah." },
        { "term": "ingat ↔ lupa", "definition": "Antonim memori.", "template": "Saya ingat janji itu — dia sudah lupa." }
      ],
      "learnHTML": "<p>Mengetahui <strong>sinonim</strong> dan <strong>antonim</strong> memberi tiga manfaat untuk PSLE:</p><ol style='margin-left:1.2rem;line-height:1.7'><li><strong>Karangan</strong>: pelbagaikan kosa kata supaya tidak ulang perkataan yang sama.</li><li><strong>Kefahaman</strong>: kenal sinonim → faham makna dalam konteks.</li><li><strong>Lisan</strong>: kosa kata yang luas membuka pintu untuk perbualan yang lebih lancar.</li></ol><p>Strategi: setiap kali anda belajar perkataan baharu, cari <strong>satu sinonim</strong> dan <strong>satu antonim</strong>. Bina hubungan triadic — itu yang memori panjang.</p><p>Lihat <code>SinonimAntonim_KB.md</code> dalam knowledge-base untuk senarai penuh.</p>",
      "summaryHTML": "<ul><li>Sinonim = seerti; Antonim = berlawanan.</li><li>Pelbagaikan perkataan dalam karangan supaya tidak monoton.</li><li>Antonim langsung lebih kuat daripada antonim dengan 'tidak'.</li><li>Belajar dalam triad: perkataan + sinonim + antonim.</li></ul>",
      "pslePrompts": [
        "Selepas menulis perenggan karangan, baca semula. Adakah ada perkataan yang berulang? Gantikan dengan sinonim.",
        "Dalam kefahaman, jika perkataan dalam soalan tidak biasa, fikirkan sinonimnya dalam petikan.",
        "Antonim langsung (kaya/miskin) lebih berkesan daripada 'tidak kaya' dalam karangan."
      ],
      "questions": [
        { "id": "sa-1", "tier": "asas", "question": "Sinonim untuk 'pandai':", "options": ["malas", "cerdik", "marah", "kecil"], "correct": 1, "explanation": "Cerdik = clever, smart (sinonim untuk pandai)." },
        { "id": "sa-2", "tier": "asas", "question": "Antonim untuk 'tinggi':", "options": ["panjang", "rendah", "lebar", "tebal"], "correct": 1, "explanation": "Tinggi ↔ rendah." },
        { "id": "sa-3", "tier": "asas", "question": "Sinonim untuk 'gembira':", "options": ["sedih", "riang", "marah", "takut"], "correct": 1, "explanation": "Riang = cheerful (sinonim untuk gembira)." },
        { "id": "sa-4", "tier": "asas", "question": "Antonim untuk 'rajin':", "options": ["tekun", "gigih", "malas", "pandai"], "correct": 2, "explanation": "Rajin ↔ malas." },
        { "id": "sa-5", "tier": "pertengahan", "question": "Pilih sinonim PALING formal untuk 'cantik':", "options": ["jelita", "cute", "okay", "biasa"], "correct": 0, "explanation": "Jelita = sinonim formal/literari untuk cantik. Sesuai untuk karangan deskriptif." },
        { "id": "sa-6", "tier": "pertengahan", "question": "Antonim untuk 'kaya':", "options": ["miskin", "tenang", "muda", "panjang"], "correct": 0, "explanation": "Kaya ↔ miskin." },
        { "id": "sa-7", "tier": "pertengahan", "question": "Sinonim untuk 'jujur':", "options": ["bohong", "ikhlas", "marah", "sedih"], "correct": 1, "explanation": "Ikhlas / amanah = sinonim untuk jujur." },
        { "id": "sa-8", "tier": "pertengahan", "question": "Pilih antonim untuk 'bersih':", "options": ["cerah", "kotor", "panjang", "luas"], "correct": 1, "explanation": "Bersih ↔ kotor." },
        { "id": "sa-9", "tier": "mencabar", "question": "Sinonim PALING tepat untuk 'penat' dalam ayat formal:", "options": ["okay", "letih", "happy", "marah"], "correct": 1, "explanation": "Letih / lelah / lesu = sinonim untuk penat. 'Letih' paling biasa dalam karangan." },
        { "id": "sa-10", "tier": "mencabar", "question": "Pilih ayat yang menggunakan antonim untuk KESAN dramatik:", "options": ["Walaupun kaya, dia tetap rendah hati.", "Dia kaya dan tinggi.", "Dia kaya tetapi panjang.", "Dia rendah dan miskin."], "correct": 0, "explanation": "Antonim langsung (kaya / rendah hati) dalam satu ayat = kontras yang berkesan untuk karangan." },
        { "id": "sa-11", "tier": "mencabar", "question": "Sinonim untuk 'berani':", "options": ["pengecut", "gentar", "gagah", "lemah"], "correct": 2, "explanation": "Gagah / perkasa = sinonim untuk berani." },
        { "id": "sa-12", "tier": "mencabar", "question": "Pilih ayat yang menggunakan SINONIM untuk mengelakkan pengulangan:", "options": ["Adik gembira. Saya juga gembira. Semua gembira.", "Adik berasa gembira. Saya pula berasa riang. Suasana menjadi meriah.", "Adik happy, saya happy juga.", "Gembira gembira gembira."], "correct": 1, "explanation": "Ayat kedua: gembira → riang → meriah. Pelbagai sinonim untuk satu mood = karangan matang." }
      ]
    }
  }
}
