{
  "id": "diversity",
  "name": "Diversity",
  "tagline": "How living and non-living things are grouped and differ",
  "topics": {
    "diversity": {
      "id": "diversity",
      "title": "Diversity of Living Things",
      "themes": [
        "diversity"
      ],
      "levels": [
        "P3"
      ],
      "keyQuestions": [
        "What are the 7 characteristics shared by all living things?",
        "What is the difference between a vertebrate and an invertebrate?",
        "What are the five groups of vertebrates?",
        "How do we tell a mammal from a reptile?",
        "What is the difference between flowering and non-flowering plants?",
        "Why do scientists classify living things?"
      ],
      "keyIdeas": [],
      "glossary": [
        {
          "term": "Living thing",
          "definition": "Any organism that carries out all 7 life processes (MRS NERG). E.g. plants, animals, fungi, bacteria.",
          "template": ""
        },
        {
          "term": "Non-living thing",
          "definition": "An object that does not carry out life processes. It was never alive (e.g. rock, water) or once alive (e.g. dead wood).",
          "template": ""
        },
        {
          "term": "Vertebrate",
          "definition": "An animal with a backbone (spine). Five groups: mammals, birds, reptiles, amphibians, fish.",
          "template": ""
        },
        {
          "term": "Invertebrate",
          "definition": "An animal without a backbone. E.g. insects, spiders, worms, crabs, snails.",
          "template": ""
        },
        {
          "term": "Mammal",
          "definition": "Warm-blooded vertebrate with fur/hair; gives birth to live young (mostly) and feeds young with milk.",
          "template": ""
        },
        {
          "term": "Bird",
          "definition": "Warm-blooded vertebrate with feathers, wings, and a beak; lays hard-shelled eggs.",
          "template": ""
        },
        {
          "term": "Reptile",
          "definition": "Cold-blooded vertebrate with dry, scaly skin; lays leathery eggs on land.",
          "template": ""
        },
        {
          "term": "Amphibian",
          "definition": "Cold-blooded vertebrate with moist skin; lives in water and on land; lays eggs in water.",
          "template": ""
        },
        {
          "term": "Fish",
          "definition": "Cold-blooded vertebrate; lives in water; has scales and fins; breathes through gills.",
          "template": ""
        },
        {
          "term": "Insect",
          "definition": "An invertebrate with 3 body parts (head, thorax, abdomen), 6 legs, and usually 2 pairs of wings. E.g. ants, butterflies, bees.",
          "template": ""
        },
        {
          "term": "Classify",
          "definition": "To group living things based on shared observable characteristics so they are easier to study and remember.",
          "template": ""
        },
        {
          "term": "Characteristic",
          "definition": "A feature of a living thing that can be observed and used to sort or identify it (e.g. number of legs, body covering).",
          "template": ""
        }
      ],
      "learnHTML": "",
      "summaryHTML": "",
      "simulation": {
        "embedded": true
      },
      "pslePrompts": [],
      "questions": [],
      "phenomena": []
    },
    "materials": {
      "id": "materials",
      "title": "Diversity of Materials",
      "themes": [
        "diversity"
      ],
      "levels": [
        "P4"
      ],
      "keyQuestions": [
        "What are the five main properties used to compare materials?",
        "What does \"hardness\" mean? How is it tested?",
        "Why is copper used for electrical wires?",
        "What is a soluble substance? Give two everyday examples.",
        "What is the difference between transparent, translucent, and opaque materials?"
      ],
      "keyIdeas": [],
      "glossary": [
        {
          "term": "Hardness",
          "definition": "How resistant a material is to being scratched or dented. Tested by trying to scratch one material with another. Metals and glass are hard; rubber is soft.",
          "template": ""
        },
        {
          "term": "Flexibility",
          "definition": "How easily a material bends without breaking. Rubber and fabric are flexible; glass and metal are generally not.",
          "template": ""
        },
        {
          "term": "Transparency",
          "definition": "How much light passes through a material. Transparent (clear glass) lets all light through; translucent (frosted glass) lets some through; opaque (wood) lets none through.",
          "template": ""
        },
        {
          "term": "Water Absorption",
          "definition": "How much water a material soaks up. Cloth and paper absorb water; plastic and glass do not.",
          "template": ""
        },
        {
          "term": "Electrical Conductivity",
          "definition": "How easily a material allows electricity to flow through it. Metals (copper, aluminium) are good conductors; rubber, plastic, and glass are insulators.",
          "template": ""
        },
        {
          "term": "Thermal Conductivity",
          "definition": "How easily a material allows heat to flow through it. Metals are good thermal conductors; wood and plastic are thermal insulators.",
          "template": ""
        },
        {
          "term": "Solubility",
          "definition": "Whether a substance dissolves in water. Sugar and salt are soluble; sand and oil are insoluble.",
          "template": ""
        },
        {
          "term": "Solute",
          "definition": "The substance that dissolves (e.g. sugar or salt).",
          "template": ""
        },
        {
          "term": "Solvent",
          "definition": "The liquid that does the dissolving (water is the most common solvent).",
          "template": ""
        },
        {
          "term": "Solution",
          "definition": "The mixture formed when a solute dissolves in a solvent. A solution is clear (not cloudy).",
          "template": ""
        },
        {
          "term": "Magnetic Property",
          "definition": "Whether a material is attracted to a magnet. Iron, steel, nickel, and cobalt are magnetic. Most other materials are non-magnetic.",
          "template": ""
        },
        {
          "term": "Strength",
          "definition": "How much force a material can withstand before breaking or deforming. Steel is very strong; cardboard is weak.",
          "template": ""
        }
      ],
      "learnHTML": "",
      "summaryHTML": "",
      "simulation": {
        "embedded": true
      },
      "pslePrompts": [],
      "questions": [],
      "phenomena": []
    }
  }
}
